phpphar/__init__.py
phpphar/constants.py
phpphar/types.py
phpphar/utils.py
phpphar/io/__init__.py
phpphar/io/phar.py
phpphar/io/tar.py
phpphar/io/zip.py
libphpphar-0.0.2.dist-info/METADATA
libphpphar-0.0.2.dist-info/WHEEL
libphpphar-0.0.2.dist-info/top_level.txt
libphpphar-0.0.2.dist-info/RECORD
