Metadata-Version: 2.1
Name: libphpphar
Version: 0.0.2
Summary: generate PHP phar archives on the fly
Author-email: Frank <frankli0324@hotmail.com>
License: MIT
Project-URL: repository, https://github.com/frankli0324/libphpphar
Classifier: Programming Language :: Python :: 3
Classifier: License :: OSI Approved :: MIT License
Requires-Python: >=3.7
Requires-Dist: libphpserialize
Requires-Dist: typing-extensions ; python_version <= "3.7"
